ner_span_annotator/__init__.py
ner_span_annotator/example.py
ner_span_annotator/frontend/build/asset-manifest.json
ner_span_annotator/frontend/build/bootstrap.min.css
ner_span_annotator/frontend/build/index.html
ner_span_annotator/frontend/build/static/js/main.76d354f6.js
ner_span_annotator/frontend/build/static/js/main.76d354f6.js.LICENSE.txt
ner_span_annotator/frontend/build/static/js/main.76d354f6.js.map
ner_span_annotator/frontend/build/static/js/main.b066f690.js
ner_span_annotator/frontend/build/static/js/main.b066f690.js.LICENSE.txt
ner_span_annotator/frontend/build/static/js/main.b066f690.js.map
ner_span_annotator/frontend/build/static/js/main.c22951e9.js
ner_span_annotator/frontend/build/static/js/main.c22951e9.js.LICENSE.txt
ner_span_annotator/frontend/build/static/js/main.c22951e9.js.map
ner_span_annotator-0.2.1.dist-info/LICENSE
ner_span_annotator-0.2.1.dist-info/METADATA
ner_span_annotator-0.2.1.dist-info/WHEEL
ner_span_annotator-0.2.1.dist-info/top_level.txt
ner_span_annotator-0.2.1.dist-info/RECORD
